{
  "packages": [
    {
      "maintainer": "Gimasi SA",
      "websiteURL": "http://www.gimasi.ch",
      "email": "info@giamsi.ch",
      "name": "Tuino",
      "platforms": [
        {
          "name": "Tuino AVR Boards",
          "architecture": "avr",
          "version": "1.0.2",
          "category": "Contributed",         
          "help": {
            "online": "http://www.tuino.io"
          },
          "url": "https://raw.githubusercontent.com/gimasi/TUINO_ONE/master/arduino_ide/tuino-1.0.2.zip",
          "archiveFileName": "tuino-1.0.2.zip",
          "checksum": "SHA-256:70C6F570D40CB96F0B462D4A00F658D8BB4DAA020FF2DF886A7DB4514B2D9957",
          "size": "14667",
          "toolsDependencies": [
            {
              "packager": "arduino",
              "version": "4.8.1-arduino5",
              "name": "avr-gcc"
            },
            {
              "packager": "arduino",
              "version": "6.0.1-arduino5",
              "name": "avrdude"
            }
          ],
          "boards": [
            {
              "name": "Tuino 1"
            }
          ]
        }
      ],
      "tools": [] 
    }
  ]
}


